qualo/__init__.py
qualo/api.py
qualo/constants.py
qualo/draw_hierarchy.py
qualo/lint.py
qualo/prefixes.py
qualo/py.typed
qualo/version.py
qualo/curate/__init__.py
qualo/curate/ensure_disciplines.py
qualo/curate/import_orcid_downloader_dictionary.py
qualo/curate/import_orcid_ungrounded.py
qualo/data/__init__.py
qualo/data/conferrers.tsv
qualo/data/disciplines.tsv
qualo/data/holders.tsv
qualo/data/mappings.sssom.tsv
qualo/data/synonyms.tsv
qualo/data/terms.tsv
qualo-0.0.2.dist-info/licenses/LICENSE
qualo-0.0.2.dist-info/METADATA
qualo-0.0.2.dist-info/WHEEL
qualo-0.0.2.dist-info/entry_points.txt
qualo-0.0.2.dist-info/top_level.txt
qualo-0.0.2.dist-info/RECORD
