Metadata-Version: 2.4
Name: qualo
Version: 0.0.2
Summary: NLP tools for qualifications and distinctions
Author-email: Charles Tapley Hoyt <cthoyt@gmail.com>
Maintainer-email: Charles Tapley Hoyt <cthoyt@gmail.com>
License: MIT License
Project-URL: Bug Tracker, https://github.com/cthoyt/qualo/issues
Project-URL: Homepage, https://github.com/cthoyt/qualo
Project-URL: Repository, https://github.com/cthoyt/qualo.git
Project-URL: Documentation, https://qualo.readthedocs.io
Keywords: snekpack,cookiecutter
Classifier: Development Status :: 1 - Planning
Classifier: Environment :: Console
Classifier: Intended Audience :: Developers
Classifier: License :: OSI Approved :: MIT License
Classifier: Operating System :: OS Independent
Classifier: Framework :: Pytest
Classifier: Framework :: tox
Classifier: Framework :: Sphinx
Classifier: Programming Language :: Python
Classifier: Programming Language :: Python :: 3.10
Classifier: Programming Language :: Python :: 3.11
Classifier: Programming Language :: Python :: 3.12
Classifier: Programming Language :: Python :: 3 :: Only
Requires-Python: >=3.10
License-File: LICENSE
Requires-Dist: click
Requires-Dist: pandas
Requires-Dist: curies>=0.9.0
Requires-Dist: ssslm>=0.0.17
Requires-Dist: regex
Provides-Extra: tests
Requires-Dist: pytest; extra == "tests"
Requires-Dist: coverage; extra == "tests"
Provides-Extra: nlp
Requires-Dist: pyobo; extra == "nlp"
Requires-Dist: ssslm[gilda-slim]; extra == "nlp"
Provides-Extra: docs
Requires-Dist: sphinx>=8; extra == "docs"
Requires-Dist: sphinx-rtd-theme>=3.0; extra == "docs"
Requires-Dist: sphinx-click; extra == "docs"
Requires-Dist: sphinx_automodapi; extra == "docs"
Dynamic: license-file
